vo2dict.py
voevent2dict-0.1.0.dist-info/METADATA
voevent2dict-0.1.0.dist-info/WHEEL
voevent2dict-0.1.0.dist-info/top_level.txt
voevent2dict-0.1.0.dist-info/RECORD
